arketip/__init__.py
arketip/_version.py
arketip/arketip.py
arketip/cached.py
arketip/py.typed
arketip/registry.py
arketip/types.py
arketip-0.5.dist-info/LICENSE
arketip-0.5.dist-info/METADATA
arketip-0.5.dist-info/WHEEL
arketip-0.5.dist-info/top_level.txt
arketip-0.5.dist-info/RECORD
