Metadata-Version: 2.1
Name: arketip
Version: 0.5
Summary: automatic typeguards
Home-page: https://gitlab.com/dockable/arketip.git
Author: Martin Zihlmann
Author-email: martizih@outlook.com
License: MIT
Classifier: Programming Language :: Python :: 3
Classifier: License :: Other/Proprietary License
Classifier: Operating System :: OS Independent
Requires-Python: >=3.10
License-File: LICENSE
Requires-Dist: toolz
